StudentAssist/__init__.py
StudentAssist/config.json
StudentAssist/config.py
StudentAssist/db_connector.py
StudentAssist/login.py
StudentAssist/main.py
StudentAssist/notify.py
StudentAssist/time_keeper.py
StudentAssist/database/StudentAssist.db
StudentAssist/web/static/css/Futura.ttf
StudentAssist/web/static/css/SA_style.css
StudentAssist/web/static/css/login_style.css
StudentAssist/web/static/icons/add_task.jpg
StudentAssist/web/static/icons/plus.png
StudentAssist/web/static/icons/sa-logo.png
StudentAssist/web/static/icons/sa-logo.png.pp3
StudentAssist/web/static/icons/trash.png
StudentAssist/web/static/js/login.js
StudentAssist/web/static/js/utils.js
StudentAssist/web/templates/calendar.html
StudentAssist/web/templates/home.html
StudentAssist/web/templates/login.html
StudentAssist/web/templates/settings.html
StudentAssist-1.0.1.dist-info/LICENSE
StudentAssist-1.0.1.dist-info/METADATA
StudentAssist-1.0.1.dist-info/WHEEL
StudentAssist-1.0.1.dist-info/entry_points.txt
StudentAssist-1.0.1.dist-info/top_level.txt
StudentAssist-1.0.1.dist-info/RECORD
