Metadata-Version: 2.1
Name: StudentAssist
Version: 1.0.1
Summary: StudentAssist is a Utica College CSC433 Final Project
Home-page: https://github.com/wesleyaou/CSC433
Author: A+ Labs
License: UNKNOWN
Project-URL: Bug Tracker, https://github.com/wesleyaou/CSC433/issues
Platform: UNKNOWN
Classifier: Programming Language :: Python :: 3
Classifier: License :: OSI Approved :: GNU General Public License v3 (GPLv3)
Classifier: Operating System :: Unix
Requires-Python: >=3.6
Requires-Dist: bcrypt
Requires-Dist: flask
Requires-Dist: flask-security
Requires-Dist: flask-sqlalchemy
